fiddup/__init__.py
fiddup/__main__.py
fiddup/constants.py
fiddup/fiddup.py
fiddup/result.py
fiddup/views.py
fiddup-3.0.0.dist-info/LICENSE
fiddup-3.0.0.dist-info/METADATA
fiddup-3.0.0.dist-info/WHEEL
fiddup-3.0.0.dist-info/entry_points.txt
fiddup-3.0.0.dist-info/top_level.txt
fiddup-3.0.0.dist-info/RECORD
