Metadata-Version: 2.1
Name: fiddup
Version: 3.0.0
Summary: Utility to find similar files based on filename or hash.
Home-page: https://github.com/jarviscodes/fiddup
Author: Jarvis Codes
Author-email: jarvis@jayradz.com
License: MIT
Platform: UNKNOWN
Classifier: Programming Language :: Python :: 3
License-File: LICENSE
Requires-Dist: click
Requires-Dist: colorama
Requires-Dist: alive-progress
Requires-Dist: terminaltables
